download_3gpp/VERSION
download_3gpp/__init__.py
download_3gpp/download.py
download_3gpp/entrypoint.py
download_3gpp/options.py
download_3gpp/options.pyi
download_3gpp-0.7.0.dist-info/entry_points.txt
download_3gpp-0.7.0.dist-info/LICENSE
download_3gpp-0.7.0.dist-info/WHEEL
download_3gpp-0.7.0.dist-info/METADATA
download_3gpp-0.7.0.dist-info/RECORD
